bosun/__init__.py
bosun/constants.py
bosun/model_connector/__init__.py
bosun/model_connector/config_external.json
bosun/model_connector/constants.py
bosun/model_connector/file_uri_fetcher.py
bosun/model_connector/mc_bosun.py
bosun/model_connector/mc_runner.py
bosun/model_connector/model_connector_base.py
bosun/model_connector/s3_uri_fetcher.py
bosun/model_connector/uri_fetcher_base.py
bosun/plugin/__init__.py
bosun/plugin/action_status.py
bosun/plugin/bosun_plugin_base.py
bosun/plugin/bosun_test_plugin.py
bosun/plugin/constants.py
bosun/plugin/deployment_info.py
bosun/plugin/deployment_utils.py
bosun/plugin/endpoint_info.py
bosun/plugin/exceptions.py
bosun/plugin/model_package_info.py
bosun/plugin/pe_info.py
bosun/plugin/plugin_runner.py
bosun/plugin/azureml/__init__.py
bosun/plugin/azureml/azureml_plugin.py
bosun/plugin/azureml/azureml_status_reporter.py
bosun/plugin/azureml/template_renderer.py
bosun/plugin/azureml/client/base_endpoint_client.py
bosun/plugin/azureml/client/batch_endpoint_client.py
bosun/plugin/azureml/client/online_endpoint_client.py
bosun/plugin/azureml/client/scoring_snippets.py
bosun/plugin/azureml/config/__init__.py
bosun/plugin/azureml/config/azureml_client_config.py
bosun/plugin/azureml/config/config_keys.py
bosun/plugin/azureml/templates/batch_score.py
bosun/plugin/azureml/templates/common.py
bosun/plugin/azureml/templates/conda.yml
bosun/plugin/azureml/templates/online_score.py
bosun/plugin/azureml/templates/scoring_script_builder.py.j2
bosun/plugin/config_samples/__init__.py
bosun/plugin/config_samples/deployment_list_config.yaml
bosun/plugin/config_samples/deployment_replace_model_config.yaml
bosun/plugin/config_samples/deployment_start_config.yaml
bosun/plugin/config_samples/deployment_status_config.yaml
bosun/plugin/config_samples/deployment_stop_config.yaml
bosun/plugin/config_samples/endpoint_update_config.yaml
bosun/plugin/config_samples/pe_status_config.yaml
bosun/plugin/config_samples/plugin_start_config.yaml
datarobot_bosun-11.1.0.dist-info/METADATA
datarobot_bosun-11.1.0.dist-info/WHEEL
datarobot_bosun-11.1.0.dist-info/entry_points.txt
datarobot_bosun-11.1.0.dist-info/top_level.txt
datarobot_bosun-11.1.0.dist-info/RECORD
