Metadata-Version: 2.1
Name: datarobot-bosun
Version: 11.1.0
Summary: datarobot-bosun module providing MLOps Management framework and plug-ins
Home-page: http://datarobot.com
Author: DataRobot
Author-email: info@datarobot.com
License: DataRobot
Project-URL: Documentation, https://docs.datarobot.com/en/docs/release/public-preview/mlops-preview/mgmt-agent.html#mlops-management-agent
Platform: UNKNOWN
Classifier: Programming Language :: Python :: 3
Classifier: Programming Language :: Python :: 3.9
Classifier: Programming Language :: Python :: 3.10
Classifier: License :: Other/Proprietary License
Classifier: Operating System :: MacOS
Classifier: Operating System :: POSIX
Classifier: Operating System :: Unix
Requires-Python: >=3.9
Requires-Dist: pyyaml
Requires-Dist: pytz
Requires-Dist: python-dateutil
Requires-Dist: schema
Requires-Dist: datarobot-mlops-connected-client (>=10.0.3)
Provides-Extra: azureml
Requires-Dist: azure-ai-ml (>=1.3) ; extra == 'azureml'
Requires-Dist: azure-identity (>=1.12) ; extra == 'azureml'
Requires-Dist: datarobot-mlops-stats-aggregator (>=10.2.3) ; extra == 'azureml'
Provides-Extra: docker
Requires-Dist: requests ; extra == 'docker'
Requires-Dist: docker ; extra == 'docker'
Provides-Extra: kubernetes
Requires-Dist: jinja2 ; extra == 'kubernetes'
Requires-Dist: requests ; extra == 'kubernetes'
Requires-Dist: kubernetes (!=25.*,>=19.15) ; (python_version < "3.9") and extra == 'kubernetes'
Requires-Dist: kubernetes (>=19.15) ; (python_version >= "3.9") and extra == 'kubernetes'
Provides-Extra: s3
Requires-Dist: boto3 (>=1.11.4) ; extra == 's3'
Provides-Extra: sagemaker
Requires-Dist: boto3 (>=1.28.61) ; extra == 'sagemaker'
Provides-Extra: snowflake
Requires-Dist: snowflake-connector-python (>=3.7.1) ; extra == 'snowflake'
